[{"la":50.636997,"lo":4.965148,"n":"","t":"man_made=tower"},{"la":50.628795,"lo":4.973668,"n":"Branchon Église","t":"public_transport=platform"},{"la":50.628839,"lo":4.974024,"n":"Branchon Église","t":"public_transport=platform"},{"la":50.625849,"lo":5.00866,"n":"","t":"man_made=mast"},{"la":50.625099,"lo":4.955581,"n":"Boneffe Ferme Bouvier","t":"public_transport=platform"},{"la":50.625172,"lo":4.955374,"n":"Boneffe Ferme Bouvier","t":"public_transport=platform"},{"la":50.626525,"lo":4.962088,"n":"Branchon Ferme Boneffe","t":"public_transport=platform"},{"la":50.626892,"lo":4.962869,"n":"Branchon Ferme Boneffe","t":"public_transport=platform"},{"la":50.633051,"lo":4.969332,"n":"Branchon Saule Malaive","t":"public_transport=platform"},{"la":50.63288,"lo":4.969321,"n":"Branchon Saule Malaive","t":"public_transport=platform"},{"la":50.628543,"lo":4.968635,"n":"Branchon Village","t":"public_transport=platform"},{"la":50.628643,"lo":4.968064,"n":"Branchon Village","t":"public_transport=platform"},{"la":50.629805,"lo":4.972576,"n":"Branchon Église","t":"public_transport=platform"},{"la":50.6296,"lo":4.972718,"n":"Branchon Église","t":"public_transport=platform"},{"la":50.65139,"lo":5.007481,"n":"Merdorp Chemin des Hougardiers","t":"public_transport=platform"},{"la":50.651401,"lo":5.007338,"n":"Merdorp Chemin des Hougardiers","t":"public_transport=platform"},{"la":50.648972,"lo":5.001832,"n":"Merdorp Gare","t":"public_transport=platform"},{"la":50.648835,"lo":5.001961,"n":"Merdorp Gare","t":"public_transport=platform"},{"la":50.645815,"lo":5.002234,"n":"Merdorp Mare","t":"public_transport=platform"},{"la":50.646201,"lo":5.002638,"n":"Merdorp Mare","t":"public_transport=platform"},{"la":50.639067,"lo":5.004151,"n":"Merdorp Rue de Moxhe","t":"public_transport=platform"},{"la":50.639076,"lo":5.00405,"n":"Merdorp Rue de Moxhe","t":"public_transport=platform"},{"la":50.649367,"lo":4.998456,"n":"","t":"historic=monument"},{"la":50.649323,"lo":4.998448,"n":"","t":"amenity=post_box"},{"la":50.626048,"lo":4.99792,"n":"Ferme de la Dîme","t":"amenity=arts_centre"},{"la":50.625444,"lo":5.004591,"n":"BPost","t":"amenity=post_office"},{"la":50.628952,"lo":4.968333,"n":"","t":"amenity=public_bookcase"},{"la":50.638187,"lo":4.974565,"n":"","t":"man_made=mast"},{"la":50.629019,"lo":4.972202,"n":"","t":"amenity=recycling"},{"la":50.629019,"lo":4.972234,"n":"","t":"amenity=recycling"},{"la":50.649509,"lo":5.003931,"n":"Chapelle Notre-Dame des Champs","t":"historic=wayside_shrine"},{"la":50.65175,"lo":5.00786,"n":"Chapelle Sainte-Barbe","t":"historic=wayside_shrine"},{"la":50.652343,"lo":4.998597,"n":"","t":"historic=yes"},{"la":50.650789,"lo":5.006608,"n":"","t":"historic=yes"},{"la":50.648115,"lo":5.000333,"n":"","t":"historic=yes"},{"la":50.648165,"lo":5.000469,"n":"Chapelle du Vieux Bon Dieu","t":"historic=wayside_shrine"},{"la":50.641681,"lo":5.003404,"n":"","t":"historic=wayside_cross"},{"la":50.632543,"lo":4.967433,"n":"","t":"historic=wayside_shrine"},{"la":50.63256,"lo":4.967432,"n":"","t":"natural=tree"},{"la":50.647498,"lo":4.99696,"n":"","t":"amenity=public_bookcase"},{"la":50.628037,"lo":4.969466,"n":"","t":"historic=wayside_chapel"},{"la":50.651326,"lo":4.981657,"n":"","t":"natural=tree"},{"la":50.651068,"lo":4.98189,"n":"","t":"natural=tree"},{"la":50.651129,"lo":4.981588,"n":"","t":"natural=tree"},{"la":50.651121,"lo":4.981458,"n":"","t":"natural=tree"},{"la":50.647888,"lo":4.992194,"n":"","t":"natural=tree"},{"la":50.647814,"lo":4.992759,"n":"","t":"natural=tree"},{"la":50.648163,"lo":4.993156,"n":"","t":"natural=tree"},{"la":50.647892,"lo":4.992648,"n":"","t":"natural=tree"},{"la":50.647984,"lo":4.992574,"n":"","t":"natural=tree"},{"la":50.647536,"lo":4.993085,"n":"","t":"natural=tree"},{"la":50.648138,"lo":4.994782,"n":"","t":"natural=tree"},{"la":50.648646,"lo":4.990933,"n":"","t":"natural=tree"},{"la":50.648853,"lo":4.991065,"n":"","t":"natural=tree"},{"la":50.648419,"lo":4.991186,"n":"","t":"natural=tree"},{"la":50.649195,"lo":4.994135,"n":"","t":"natural=tree"},{"la":50.649144,"lo":4.994461,"n":"","t":"natural=tree"},{"la":50.649225,"lo":4.994699,"n":"","t":"natural=tree"},{"la":50.649578,"lo":4.995677,"n":"","t":"natural=tree"},{"la":50.648908,"lo":4.997821,"n":"","t":"natural=tree"},{"la":50.649428,"lo":4.99852,"n":"","t":"natural=tree"},{"la":50.646727,"lo":4.996947,"n":"","t":"natural=tree"},{"la":50.64665,"lo":4.99714,"n":"","t":"natural=tree"},{"la":50.649431,"lo":4.999379,"n":"","t":"natural=tree"},{"la":50.649057,"lo":4.999096,"n":"","t":"natural=tree"},{"la":50.651896,"lo":4.997058,"n":"","t":"natural=tree"},{"la":50.651553,"lo":4.997319,"n":"","t":"natural=tree"},{"la":50.652166,"lo":4.997071,"n":"","t":"natural=tree"},{"la":50.651944,"lo":4.997549,"n":"","t":"natural=tree"},{"la":50.652201,"lo":4.99611,"n":"","t":"natural=tree"},{"la":50.652058,"lo":4.995895,"n":"","t":"natural=tree"},{"la":50.652203,"lo":4.995753,"n":"","t":"natural=tree"},{"la":50.652225,"lo":4.995538,"n":"","t":"natural=tree"},{"la":50.652719,"lo":4.996203,"n":"","t":"natural=tree"},{"la":50.652881,"lo":4.997212,"n":"","t":"natural=tree"},{"la":50.644518,"lo":5.001898,"n":"","t":"natural=tree"},{"la":50.643631,"lo":5.002813,"n":"","t":"natural=tree"},{"la":50.643671,"lo":5.00301,"n":"","t":"natural=tree"},{"la":50.642324,"lo":5.002061,"n":"","t":"natural=tree"},{"la":50.647046,"lo":5.003621,"n":"","t":"natural=tree"},{"la":50.646954,"lo":5.003518,"n":"","t":"natural=tree"},{"la":50.648864,"lo":5.003045,"n":"","t":"natural=tree"},{"la":50.650023,"lo":4.999022,"n":"","t":"natural=tree"},{"la":50.650088,"lo":4.998863,"n":"","t":"natural=tree"},{"la":50.650087,"lo":4.998292,"n":"","t":"natural=tree"},{"la":50.650323,"lo":4.997881,"n":"","t":"natural=tree"},{"la":50.650651,"lo":4.997955,"n":"","t":"natural=tree"},{"la":50.650382,"lo":5.007691,"n":"","t":"natural=tree"},{"la":50.650586,"lo":5.007991,"n":"","t":"natural=tree"},{"la":50.651348,"lo":5.00612,"n":"","t":"natural=tree"},{"la":50.651526,"lo":5.006802,"n":"","t":"natural=tree"},{"la":50.651062,"lo":5.005569,"n":"","t":"natural=tree"},{"la":50.637126,"lo":4.979792,"n":"","t":"amenity=hunting_stand"},{"la":50.651615,"lo":4.971792,"n":"","t":"natural=tree"},{"la":50.651673,"lo":4.982823,"n":"","t":"natural=tree"},{"la":50.651693,"lo":4.982621,"n":"","t":"natural=tree"},{"la":50.628596,"lo":4.968608,"n":"","t":"public_transport=stop_position"},{"la":50.649925,"lo":4.923403,"n":"","t":"amenity=recycling"},{"la":50.649914,"lo":4.923381,"n":"","t":"amenity=recycling"},{"la":50.649721,"lo":4.998928,"n":"Église Saint-Remy","t":"amenity=place_of_worship"},{"la":50.649715,"lo":4.998917,"n":"Église Saint-Remy","t":"amenity=place_of_worship"},{"la":50.647275,"lo":4.992157,"n":"","t":"leisure=pitch"},{"la":50.647275,"lo":4.992157,"n":"","t":"leisure=pitch"},{"la":50.625379,"lo":5.008273,"n":"","t":"leisure=pitch"},{"la":50.62527,"lo":5.007754,"n":"FCE Wasseiges","t":"amenity=community_centre"},{"la":50.625379,"lo":5.008273,"n":"","t":"leisure=pitch"},{"la":50.62527,"lo":5.007754,"n":"FCE Wasseiges","t":"amenity=community_centre"},{"la":50.628881,"lo":4.97229,"n":"Église Saint-Jean-Baptiste","t":"amenity=place_of_worship"},{"la":50.628881,"lo":4.97229,"n":"Église Saint-Jean-Baptiste","t":"amenity=place_of_worship"},{"la":50.630512,"lo":4.972208,"n":"","t":"natural=tree_row"},{"la":50.62608,"lo":4.994841,"n":"","t":"natural=tree_row"},{"la":50.626818,"lo":4.979974,"n":"","t":"natural=tree_row"},{"la":50.626884,"lo":4.972279,"n":"","t":"natural=tree_row"},{"la":50.62712,"lo":4.979502,"n":"","t":"natural=tree_row"},{"la":50.627385,"lo":4.97554,"n":"","t":"natural=tree_row"},{"la":50.626607,"lo":4.962435,"n":"","t":"natural=tree_row"},{"la":50.6475,"lo":4.997032,"n":"École communale de Merdorp","t":"amenity=school"},{"la":50.647447,"lo":4.997006,"n":"École communale de Merdorp","t":"amenity=school"},{"la":50.649192,"lo":4.998523,"n":"","t":"amenity=parking"},{"la":50.650255,"lo":4.997533,"n":"","t":"leisure=park"},{"la":50.650117,"lo":4.997599,"n":"Château de Merdorp","t":"historic=castle"},{"la":50.649553,"lo":4.998096,"n":"","t":"man_made=tower"},{"la":50.650226,"lo":4.996944,"n":"","t":"natural=water"},{"la":50.648671,"lo":5.000359,"n":"Ferme Dandoy","t":"historic=yes"},{"la":50.648417,"lo":5.001478,"n":"Ferme Saint-Jean","t":"historic=yes"},{"la":50.649192,"lo":4.998523,"n":"","t":"amenity=parking"},{"la":50.650221,"lo":4.997448,"n":"","t":"leisure=park"},{"la":50.650158,"lo":4.997599,"n":"Château de Merdorp","t":"historic=castle"},{"la":50.649553,"lo":4.998088,"n":"","t":"man_made=tower"},{"la":50.650221,"lo":4.996941,"n":"","t":"natural=water"},{"la":50.648665,"lo":5.000353,"n":"Ferme Dandoy","t":"historic=yes"},{"la":50.648406,"lo":5.001453,"n":"Ferme Saint-Jean","t":"historic=yes"},{"la":50.648567,"lo":5.003149,"n":"","t":"natural=scrub"},{"la":50.644519,"lo":5.006066,"n":"","t":"natural=scrub"},{"la":50.644048,"lo":5.005841,"n":"","t":"natural=scrub"},{"la":50.648567,"lo":5.003149,"n":"","t":"natural=scrub"},{"la":50.644519,"lo":5.006066,"n":"","t":"natural=scrub"},{"la":50.644048,"lo":5.005841,"n":"","t":"natural=scrub"},{"la":50.649335,"lo":4.996161,"n":"Ferme de Sainte-Colombe","t":"amenity=events_venue"},{"la":50.652299,"lo":4.927859,"n":"","t":"natural=wood"},{"la":50.652281,"lo":4.927848,"n":"","t":"natural=wood"},{"la":50.625979,"lo":4.995079,"n":"","t":"leisure=pitch"},{"la":50.625966,"lo":4.999275,"n":"","t":"natural=wood"},{"la":50.625977,"lo":4.995023,"n":"","t":"leisure=pitch"},{"la":50.626035,"lo":4.999169,"n":"","t":"natural=wood"},{"la":50.625178,"lo":4.997887,"n":"Ferme du Château de Wasseiges","t":"historic=farm"},{"la":50.625502,"lo":4.979742,"n":"","t":"natural=water"},{"la":50.625672,"lo":4.979098,"n":"","t":"natural=water"},{"la":50.625502,"lo":4.979742,"n":"","t":"natural=water"},{"la":50.625622,"lo":4.979051,"n":"","t":"natural=water"},{"la":50.646677,"lo":4.929503,"n":"","t":"natural=wood"},{"la":50.645112,"lo":4.931466,"n":"","t":"leisure=swimming_pool"},{"la":50.646594,"lo":4.929492,"n":"","t":"natural=wood"},{"la":50.645113,"lo":4.931465,"n":"","t":"leisure=swimming_pool"},{"la":50.649403,"lo":4.999069,"n":"Presbytère","t":"historic=yes"},{"la":50.651359,"lo":4.997873,"n":"Ferme Dechentinnes.","t":"historic=yes"},{"la":50.649371,"lo":4.999028,"n":"Presbytère","t":"historic=yes"},{"la":50.651364,"lo":4.997837,"n":"Ferme Dechentinnes.","t":"historic=yes"},{"la":50.627607,"lo":4.966623,"n":"","t":"leisure=pitch"},{"la":50.628054,"lo":4.967808,"n":"Château de Branchon","t":"historic=yes"},{"la":50.626892,"lo":4.967804,"n":"","t":"natural=water"},{"la":50.627607,"lo":4.966623,"n":"","t":"leisure=pitch"},{"la":50.628022,"lo":4.967808,"n":"Château de Branchon","t":"historic=yes"},{"la":50.62689,"lo":4.967799,"n":"","t":"natural=water"},{"la":50.631118,"lo":4.969181,"n":"Aire de loisirs","t":"natural=scrub"},{"la":50.631127,"lo":4.96918,"n":"Aire de loisirs","t":"natural=scrub"},{"la":50.628668,"lo":5.004123,"n":"","t":"amenity=parking"},{"la":50.628645,"lo":5.004058,"n":"","t":"amenity=parking"},{"la":50.629579,"lo":4.974237,"n":"Château Gréban","t":"historic=castle"},{"la":50.628952,"lo":4.968526,"n":"Le Foyer","t":"amenity=community_centre"},{"la":50.628839,"lo":4.968541,"n":"Ancienne Presbytère","t":"historic=yes"},{"la":50.629573,"lo":4.974214,"n":"Château Gréban","t":"historic=castle"},{"la":50.628956,"lo":4.968495,"n":"Le Foyer","t":"amenity=community_centre"},{"la":50.628833,"lo":4.968522,"n":"Ancienne Presbytère","t":"historic=yes"},{"la":50.629106,"lo":4.97231,"n":"","t":"amenity=parking"},{"la":50.627847,"lo":4.970894,"n":"Moulin de Branchon","t":"man_made=watermill"},{"la":50.629094,"lo":4.972309,"n":"","t":"amenity=parking"},{"la":50.627847,"lo":4.970894,"n":"Moulin de Branchon","t":"man_made=watermill"},{"la":50.625169,"lo":4.954854,"n":"Chapelle Saint-Pierre","t":"amenity=place_of_worship"},{"la":50.625102,"lo":5.007842,"n":"FCE Wasseiges","t":"leisure=sports_centre"},{"la":50.631124,"lo":4.973329,"n":"","t":"natural=scrub"},{"la":50.629752,"lo":4.972228,"n":"Ferme Rigo","t":"historic=yes"},{"la":50.625167,"lo":4.95485,"n":"Chapelle Saint-Pierre","t":"amenity=place_of_worship"},{"la":50.631124,"lo":4.973329,"n":"","t":"natural=scrub"},{"la":50.629744,"lo":4.972207,"n":"Ferme Rigo","t":"historic=yes"},{"la":50.62824,"lo":4.968467,"n":"Ferme du Château","t":"historic=yes"},{"la":50.627658,"lo":4.970799,"n":"","t":"man_made=chimney"},{"la":50.627658,"lo":4.970799,"n":"","t":"man_made=chimney"},{"la":50.649037,"lo":4.998823,"n":"Ancienne maison communale","t":"historic=yes"},{"la":50.643104,"lo":5.003638,"n":"","t":"amenity=place_of_worship"},{"la":50.625286,"lo":4.957735,"n":"","t":"amenity=place_of_worship"},{"la":50.625351,"lo":4.9581,"n":"","t":"natural=tree_row"},{"la":50.625106,"lo":4.95858,"n":"","t":"natural=tree_row"},{"la":50.627033,"lo":4.967936,"n":"","t":"natural=wetland"},{"la":50.649037,"lo":4.998823,"n":"Ancienne maison communale","t":"historic=yes"},{"la":50.643104,"lo":5.003638,"n":"","t":"amenity=place_of_worship"},{"la":50.625286,"lo":4.957735,"n":"","t":"amenity=place_of_worship"},{"la":50.627016,"lo":4.967909,"n":"","t":"natural=wetland"},{"la":50.650111,"lo":4.998068,"n":"","t":"man_made=tower"},{"la":50.649932,"lo":4.998071,"n":"Tourelles & Mur","t":"man_made=tower"},{"la":50.63698,"lo":4.99702,"n":"","t":"natural=scrub"},{"la":50.638251,"lo":4.996745,"n":"Tombes de Mirtaux","t":"historic=archaeological_site"},{"la":50.650111,"lo":4.998058,"n":"","t":"man_made=tower"},{"la":50.649932,"lo":4.99806,"n":"Tourelles & Mur","t":"man_made=tower"},{"la":50.636979,"lo":4.99702,"n":"","t":"natural=scrub"},{"la":50.638252,"lo":4.996723,"n":"Tombes de Mirtaux","t":"historic=archaeological_site"},{"la":50.630378,"lo":4.972517,"n":"","t":"amenity=place_of_worship"},{"la":50.630378,"lo":4.972517,"n":"","t":"amenity=place_of_worship"},{"la":50.626363,"lo":4.973329,"n":"","t":"amenity=place_of_worship"},{"la":50.626364,"lo":4.973328,"n":"","t":"amenity=place_of_worship"},{"la":50.638457,"lo":4.993719,"n":"","t":"natural=scrub"},{"la":50.638457,"lo":4.993719,"n":"","t":"natural=scrub"},{"la":50.641827,"lo":5.007824,"n":"","t":"natural=scrub"},{"la":50.642606,"lo":4.933454,"n":"","t":"natural=scrub"},{"la":50.641827,"lo":5.007824,"n":"","t":"natural=scrub"},{"la":50.642521,"lo":4.933387,"n":"","t":"natural=scrub"},{"la":50.625217,"lo":4.95937,"n":"","t":"leisure=pitch"},{"la":50.652361,"lo":4.982734,"n":"","t":"leisure=pitch"},{"la":50.625217,"lo":4.95937,"n":"","t":"leisure=pitch"},{"la":50.652304,"lo":4.982661,"n":"","t":"leisure=pitch"},{"la":50.645599,"lo":4.970307,"n":"","t":"natural=tree_row"},{"la":50.646895,"lo":5.002406,"n":"","t":"natural=tree_row"},{"la":50.649717,"lo":4.972618,"n":"","t":"natural=water"},{"la":50.652861,"lo":4.973605,"n":"Ancienne école","t":"historic=yes"},{"la":50.647686,"lo":4.992805,"n":"","t":"natural=tree_row"},{"la":50.648488,"lo":4.99145,"n":"","t":"natural=tree_row"},{"la":50.649639,"lo":4.995006,"n":"","t":"natural=tree_row"},{"la":50.649763,"lo":4.995307,"n":"","t":"natural=tree_row"},{"la":50.649526,"lo":4.9949,"n":"","t":"natural=tree_row"},{"la":50.648397,"lo":4.995854,"n":"","t":"natural=tree_row"},{"la":50.649445,"lo":4.99949,"n":"","t":"natural=tree_row"},{"la":50.652222,"lo":4.99987,"n":"","t":"natural=tree_row"},{"la":50.643171,"lo":5.002762,"n":"","t":"natural=tree_row"},{"la":50.643113,"lo":5.002845,"n":"","t":"natural=tree_row"},{"la":50.650931,"lo":4.998659,"n":"","t":"leisure=swimming_pool"},{"la":50.649713,"lo":4.972614,"n":"","t":"natural=water"},{"la":50.65286,"lo":4.973604,"n":"Ancienne école","t":"historic=yes"},{"la":50.650921,"lo":4.998658,"n":"","t":"leisure=swimming_pool"},{"la":50.632657,"lo":4.966926,"n":"","t":"amenity=place_of_worship"},{"la":50.652215,"lo":4.983079,"n":"","t":"natural=tree_row"},{"la":50.652738,"lo":4.982384,"n":"","t":"natural=tree_row"},{"la":50.632657,"lo":4.966921,"n":"","t":"amenity=place_of_worship"},{"la":50.628853,"lo":4.974005,"n":"","t":"amenity=shelter"},{"la":50.632854,"lo":4.969292,"n":"","t":"amenity=shelter"},{"la":50.628645,"lo":4.968102,"n":"","t":"amenity=shelter"},{"la":50.625172,"lo":4.955318,"n":"","t":"amenity=shelter"},{"la":50.628854,"lo":4.973999,"n":"","t":"amenity=shelter"},{"la":50.632854,"lo":4.969292,"n":"","t":"amenity=shelter"},{"la":50.628645,"lo":4.968102,"n":"","t":"amenity=shelter"},{"la":50.625172,"lo":4.955318,"n":"","t":"amenity=shelter"}]